Lesson2/fn_sw_4.v
//四选一逻辑的实现 -- case语句
`timescale 1ns/10ps
module fn_sw_4(
            a,
            b,
            sel,
            y
);
input       a;
input       b;
input[1:0]  sel;
output      y;

reg y;      //always 内部赋值的变量需要类型为reg
always @(a or b or sel) begin
    case (sel)
        2'b00:begin y<=a&b; end
        2'b01:begin y<=a|b; end
        2'b10:begin y<=a^b; end
        2'b11:begin y<=~(a^b); end 
    endcase
end
endmodule

module fn_sw_4_tb;
reg[3:0]    absel;
wire        yy;
fn_sw_4 fn_sw_4(
        .a(absel[0]),
        .b(absel[1]),
        .sel(absel[3:2]),
        .y(yy)
);

initial begin
            absel<=0;
    #200    $stop;
end
always #10 absel<=absel+1;      //使用数组进行遍历

initial begin
    $dumpfile("fn_sw_4_tb.vcd"); // 指定用作dumpfile的文件
    $dumpvars; // dump all vars
end
endmodule

Lesson2/fn_sw_4_tb.vcd
$date
	Thu May 26 17:17:32 2022
$end
$version
	Icarus Verilog
$end
$timescale
	10ps
$end
$scope module fn_sw_4_tb $end
$var wire 1 ! yy $end
$var reg 4 " absel [3:0] $end
$scope module fn_sw_4 $end
$var wire 1 # a $end
$var wire 1 $ b $end
$var wire 2 % sel [1:0] $end
$var reg 1 ! y $end
$upscope $end
$upscope $end
$enddefinitions $end
#0
$dumpvars
b0 %
0$
0#
b0 "
0!
$end
#1000
1#
b1 "
#2000
0#
1$
b10 "
#3000
1!
1#
b11 "
#4000
0!
0#
0$
b1 %
b100 "
#5000
1!
1#
b101 "
#6000
0#
1$
b110 "
#7000
1#
b111 "
#8000
0!
0#
0$
b10 %
b1000 "
#9000
1!
1#
b1001 "
#10000
0#
1$
b1010 "
#11000
0!
1#
b1011 "
#12000
1!
0#
0$
b11 %
b1100 "
#13000
0!
1#
b1101 "
#14000
0#
1$
b1110 "
#15000
1!
1#
b1111 "
#16000
0!
0#
0$
b0 %
b0 "
#17000
1#
b1 "
#18000
0#
1$
b10 "
#19000
1!
1#
b11 "
