Lesson3/7seg_led/7seg_dec.v
//七段数码管译码器
`timescale 1ns/10ps
module seg_dec(num, a_g);
input[3:0]      num;
output[6:0]     a_g;  //a_g -> [abcdefg]
reg[6:0]        a_g;
always @(num) begin
    case(num)
        4'd0:begin a_g<=7'b1111110; end
        4'd1:begin a_g<=7'b0110000; end
        4'd2:begin a_g<=7'b1101101; end
        4'd3:begin a_g<=7'b1111001; end
        4'd4:begin a_g<=7'b0110011; end
        4'd5:begin a_g<=7'b1011011; end
        4'd6:begin a_g<=7'b1011111; end
        4'd7:begin a_g<=7'b1110000; end
        4'd8:begin a_g<=7'b1111111; end
        4'd9:begin a_g<=7'b1111011; end
        default:
             begin a_g<=7'b0000001; end
    endcase
end
endmodule

module seg_dec_tb;
reg[3:0]    n;
wire[6:0]   ag;
seg_dec seg_dec(
    .num(n),
    .a_g(ag)
);
initial begin
            n<=4'b0000;
    #120    $stop;
end
always #10 n<=n+1;
initial begin
    $dumpfile("seg_dec_tb.vcd");
    $dumpvars;
end
endmodule

Lesson3/7seg_led/seg_dec_tb.vcd
$date
	Thu May 26 20:24:32 2022
$end
$version
	Icarus Verilog
$end
$timescale
	10ps
$end
$scope module seg_dec_tb $end
$var wire 7 ! ag [6:0] $end
$var reg 4 " n [3:0] $end
$scope module seg_dec $end
$var wire 4 # num [3:0] $end
$var reg 7 $ a_g [6:0] $end
$upscope $end
$upscope $end
$enddefinitions $end
#0
$dumpvars
b1111110 $
b0 #
b0 "
b1111110 !
$end
#1000
b110000 !
b110000 $
b1 "
b1 #
#2000
b1101101 !
b1101101 $
b10 "
b10 #
#3000
b1111001 !
b1111001 $
b11 "
b11 #
#4000
b110011 !
b110011 $
b100 "
b100 #
#5000
b1011011 !
b1011011 $
b101 "
b101 #
#6000
b1011111 !
b1011111 $
b110 "
b110 #
#7000
b1110000 !
b1110000 $
b111 "
b111 #
#8000
b1111111 !
b1111111 $
b1000 "
b1000 #
#9000
b1111011 !
b1111011 $
b1001 "
b1001 #
#10000
b1 !
b1 $
b1010 "
b1010 #
#11000
b1011 "
b1011 #
